ConsoleMessenger.py
console_messenger-0.0.2.dist-info/LICENSE
console_messenger-0.0.2.dist-info/METADATA
console_messenger-0.0.2.dist-info/WHEEL
console_messenger-0.0.2.dist-info/top_level.txt
console_messenger-0.0.2.dist-info/RECORD
