Metadata-Version: 2.1
Name: console-messenger
Version: 0.0.2
Summary: This module helps to print messages in different colours on terminal & various python IDEs using rich module.
Home-page: https://github.com/Ajay2810-hub/console-messenger
Author: Ajay Lingayat
Author-email: lingayatajay2810@gmail.com
License: UNKNOWN
Platform: UNKNOWN
Classifier: Programming Language :: Python :: 3
Classifier: Programming Language :: Python :: 3.5
Classifier: Programming Language :: Python :: 3.6
Classifier: Programming Language :: Python :: 3.7
Classifier: Programming Language :: Python :: 3.8
Classifier: License :: OSI Approved :: MIT License
Classifier: Natural Language :: English
Classifier: Operating System :: OS Independent
Requires-Python: >=3.0
Requires-Dist: rich
Provides-Extra: dev
Requires-Dist: pytest (>=3.6) ; extra == 'dev'
